sphinxcontrib/__init__.py
sphinxcontrib/yogosyu/user_ordered_index_patch.py
sphinxcontrib/yogosyu/yogosyu.py
sphinxcontrib/yogosyu/__init__.py
sphinxcontrib/yogosyu/doc/conf.py
sphinxcontrib/yogosyu/doc/index.rst
sphinxcontrib/yogosyu/doc/make.bat
sphinxcontrib/yogosyu/doc/Makefile
sphinxcontrib/yogosyu/doc/module_fix_index.rst
sphinxcontrib/yogosyu/doc/module_yogosyu.rst
sphinxcontrib/yogosyu/doc/README.rst
sphinxcontrib/yogosyu/doc/README_ja.rst
sphinxcontrib/yogosyu/doc/_build/html/index.html
sphinxcontrib/yogosyu/doc/_build/html/module_fix_index.html
sphinxcontrib/yogosyu/doc/_build/html/module_yogosyu.html
sphinxcontrib/yogosyu/doc/_build/html/README.html
sphinxcontrib/yogosyu/doc/_build/html/README_ja.html
sphinxcontrib/yogosyu/doc/_build/html/search.html
sphinxcontrib/yogosyu/doc/_build/html/searchindex.js
sphinxcontrib/yogosyu/doc/_build/html/_sources/index.txt
sphinxcontrib/yogosyu/doc/_build/html/_sources/module_fix_index.txt
sphinxcontrib/yogosyu/doc/_build/html/_sources/module_yogosyu.txt
sphinxcontrib/yogosyu/doc/_build/html/_sources/README.txt
sphinxcontrib/yogosyu/doc/_build/html/_sources/README_ja.txt
sphinxcontrib/yogosyu/doc/_build/html/_static/ajax-loader.gif
sphinxcontrib/yogosyu/doc/_build/html/_static/alert_info_32.png
sphinxcontrib/yogosyu/doc/_build/html/_static/alert_warning_32.png
sphinxcontrib/yogosyu/doc/_build/html/_static/basic.css
sphinxcontrib/yogosyu/doc/_build/html/_static/bg-page.png
sphinxcontrib/yogosyu/doc/_build/html/_static/bullet_orange.png
sphinxcontrib/yogosyu/doc/_build/html/_static/classic.css
sphinxcontrib/yogosyu/doc/_build/html/_static/comment-bright.png
sphinxcontrib/yogosyu/doc/_build/html/_static/comment-close.png
sphinxcontrib/yogosyu/doc/_build/html/_static/comment.png
sphinxcontrib/yogosyu/doc/_build/html/_static/doctools.js
sphinxcontrib/yogosyu/doc/_build/html/_static/down-pressed.png
sphinxcontrib/yogosyu/doc/_build/html/_static/down.png
yogosyu-2.0.5.dist-info/DESCRIPTION.rst
yogosyu-2.0.5.dist-info/METADATA
yogosyu-2.0.5.dist-info/metadata.json
yogosyu-2.0.5.dist-info/RECORD
yogosyu-2.0.5.dist-info/top_level.txt
yogosyu-2.0.5.dist-info/WHEEL
